project_1.srcs/sources_1/new/operator.v
//////////////////////////////////////////////////////////////////////////////////
// Company: 
// Engineer: 
// 
// Create Date: 02/06/2025 03:31:29 PM
// Design Name: 
// Module Name: operator
// Project Name: 
// Target Devices: 
// Tool Versions: 
// Description: 
// 
// Dependencies: 
// 
// Revision:
// Revision 0.01 - File Created
// Additional Comments:
// 
//////////////////////////////////////////////////////////////////////////////////

module Branch_Adder(
    input [31:0] PC,                    
    input [31:0] offset,                 
    output reg [31:0] branch_target     
);

    always @(*) begin
        branch_target <= PC + (offset );  
    end

endmodule

project_1.srcs/sources_1/new/MUX.v
//////////////////////////////////////////////////////////////////////////////////
// Company: 
// Engineer: 
// 
// Create Date: 02/06/2025 03:23:48 PM
// Design Name: 
// Module Name: MUX
// Project Name: 
// Target Devices: 
// Tool Versions: 
// Description: 
// 
// Dependencies: 
// 
// Revision:
// Revision 0.01 - File Created
// Additional Comments:
// 
//////////////////////////////////////////////////////////////////////////////////


module pc_mux(
    input [31:0] pc_in,       
    input [31:0] pc_branch,   
    input pc_select,          
    output reg[31:0] pc_out  
);
   always @(*) begin
        if (pc_select==1'b0) begin
            pc_out = pc_in;  
        end else begin
            pc_out = pc_branch;      
        end
    end

endmodule   


///////////////////////
module MUX2to1 (
    input [31:0] input0,   
    input [31:0] input1,   
    input select,          
    output [31:0] out      
);

    assign out = (select) ? input1 : input0;  

endmodule
////////////////////////////////////////
module MUX2to1_DataMemory (
    input [31:0] input0,  
    input [31:0] input1,  
    input select,         
    output [31:0] out     
);

    assign out = (select) ? input1 : input0; 

endmodule

project_1.srcs/sources_1/new/Dmem.v
//////////////////////////////////////////////////////////////////////////////////
// Company: 
// Engineer: 
// 
// Create Date: 02/06/2025 03:13:15 PM
// Design Name: 
// Module Name: Dmem
// Project Name: 
// Target Devices: 
// Tool Versions: 
// Description: 
// 
// Dependencies: 
// 
// Revision:
// Revision 0.01 - File Created
// Additional Comments:
// 
//////////////////////////////////////////////////////////////////////////////////


module Data_Memory(
    input clk,               
    input rst,               
    input MemRead,           
    input MemWrite,          
    input [31:0] address,    
    input [31:0] write_data, 
    output[31:0] read_data 
);
  reg [31:0] D_Memory [63:0];

  integer k;

  assign read_data = (MemRead) ? D_Memory[address] : 32'b00;

  always @(posedge clk) begin
	D_Memory[17] = 56;
	D_Memory[15] = 65;
end 

  always @(posedge clk or posedge rst) begin
    if (rst ) begin
      for (k = 0; k < 64; k = k + 1) begin
        D_Memory[k] = 32'b00;
      end
    end else if (MemWrite) begin
      D_Memory[address] = write_data;
    end
  end

endmodule

project_1.srcs/sources_1/new/Imem.v
//////////////////////////////////////////////////////////////////////////////////
// Company: 
// Engineer: 
// 
// Create Date: 02/06/2025 09:20:42 AM
// Design Name: 
// Module Name: Imem
// Project Name: 
// Target Devices: 
// Tool Versions: 
// Description: 
// 
// Dependencies: 
// 
// Revision:
// Revision 0.01 - File Created
// Additional Comments:
// 
//////////////////////////////////////////////////////////////////////////////////
//Instruction_Memmory
module Instruction_Memory(rst, clk, read_address, instruction_out);

input rst, clk;
input [31:0] read_address;
output [31:0] instruction_out;
reg [31:0] I_Mem [63:0];  
integer k;
assign instruction_out = I_Mem[read_address];

always @(posedge clk or posedge rst)
begin
    if (rst) begin
        for (k = 0; k < 64; k = k + 1) begin 
            I_Mem[k] = 32'b00;  
        end
    end else begin
        I_Mem[0] = 32'b0000000000000000000000000000000 ;       // no operation
        I_Mem[4] = 32'b0000000_11001_10000_000_01101_0110011;    // add x13, x16, x25
        I_Mem[8] = 32'b0100000_00011_01000_000_00101_0110011;     // sub x5, x8, x3
        I_Mem[12] = 32'b0000000_00011_00010_111_00001_0110011;    // and x1, x2, x3
        I_Mem[16] = 32'b0000000_00101_00011_110_00100_0110011;    // or x4, x3, x5
        I_Mem[20] = 32'b0000000_00101_00011_100_00100_0110011;    // xor x4, x3, x5
	    I_Mem[24] = 32'b0000000_00101_00011_001_00100_0110011;    // sll x4, x3, x5
        I_Mem[28] = 32'b0000000_00101_00011_101_00100_0110011;    // srl x4, x3, x5
        I_Mem[32] = 32'b0100000_00010_00011_101_00101_0110011;    //sra x5, x3, x2
        I_Mem[36] = 32'b0000000_00010_00011_010_00101_0110011;    //slt x5, x3, x2 
        I_Mem[40]  = 32'b000000000010_10101_000_10110_0010011;     // addi x22, x21, 2
        I_Mem[44]  = 32'b000000000011_01000_110_01001_0010011;     // ori x9, x8, 3 
	    I_Mem[48] = 32'b000000000100_01000_110_01001_0010011;     // xori x9, x8, 4
	    I_Mem[52] = 32'b000000000101_00010_111_00001_0010011;     // andi x1, x2, 5
	    I_Mem[56] = 32'b000000000110_00011_001_00100_0010011;    // slli x4, x3, 6
	    I_Mem[60] = 32'b000000000111_00011_101_00100_0010011;    // srli x4, x3, 7 
	    I_Mem[64] = 32'b000000001000_00011_101_00101_0010011;    //srai x5, x3, 8
	    I_Mem[68] = 32'b000000001001_00011_010_00101_0010011;    //slti x5, x3, 9  
	    I_Mem[72]=  32'b000000000101_00011_000_01001_0000011;     // lb x9, 5(x3)
	    I_Mem[76] = 32'b000000000011_00011_001_01001_0000011;    // lh x9, 3(x3)
        I_Mem[80]= 32'b000000001111_00010_010_01000_0000011;    // lw x8, 15(x2) 
        I_Mem[84] =  32'b0000000_01111_00011_000_01000_0100011;     // sb x15, 8(x3), x3 = 12
	    I_Mem[86] =  32'b0000000_01110_00110_001_01010_0100011;     // sh x14, 10(x6), x6 = 44
	    I_Mem[90] = 32'b0000000_01110_00110_010_01100_0100011;     // sw x14, 12(x6), x6 = 44     
	    I_Mem[94] = 32'b0_000000_01001_01001_000_0110_0_1100011;     // beq x9, x9, 12, (PC + 12 if x9 = x9 
	    I_Mem[98] = 32'b0_000000_01001_01001_001_0111_0_1100011;     //bne x9, x9, 14,(PC + 14 if x9 != x9)
        I_Mem[102] =  32'b00000000000000101000_00011_0110111;     // lui x3, 40
        I_Mem[106] =  32'b0000000000000010100_00101_0010111;     // auipc x5, 20 (rd = PC + (imm << 12))
	    I_Mem[110] = 32'b0_00000000_0_0000010100_00001_1101111;         // jal x1, 20
//     I_Mem[0]  = 32'h8c080100;  // Entry 0
//I_Mem[4]  = 32'h01084820;  // Entry 1
//I_Mem[8]  = 32'h212a0002;  // Entry 2
//I_Mem[12] = 32'h01485822;  // Entry 3
//I_Mem[16] = 32'h01686024;  // Entry 4
//I_Mem[20] = 32'h01486825;  // Entry 5
//I_Mem[21] = 32'h01487027;  // Entry 6
//I_Mem[22] = 32'h3c01ffff;  // Entry 7
//I_Mem[23] = 32'h3421ffff;  // Entry 8
//I_Mem[24] = 32'h01417824;  // Entry 9
//I_Mem[25] = 32'h3c01ffff;  // Entry 10
//I_Mem[26] = 32'h3421ffff;  // Entry 11
//I_Mem[27] = 32'h01418025;  // Entry 12
//I_Mem[28] = 32'h010a882a;  // Entry 13
//I_Mem[29] = 32'h29120006;  // Entry 14
//I_Mem[30] = 32'hac120120;  // Entry 15
//I_Mem[31] = 32'h152a0003;  // Entry 16
//I_Mem[32] = 32'h12320001;  // Entry 17
//I_Mem[33] = 32'h02529020;  // Entry 18
//I_Mem[34] = 32'h08000015;  // Entry 19
//I_Mem[35] = 32'h21090001;  // Entry 20
//I_Mem[36] = 32'h01085020;  // Entry 21
        
    end
end

endmodule
module immediate_generator(
    input [31:0] instruction,    
    output reg [31:0] imm_out   
);

    always @(*) begin
        case (instruction[6:0]) 
	    7'b0010011: imm_out = {{20{instruction[31]}}, instruction[31:20]}; // I-type  
            7'b0000011: imm_out = {{20{instruction[31]}}, instruction[31:20]}; // Load-type
            7'b0100011: imm_out = {{20{instruction[31]}}, instruction[31:25], instruction[11:7]}; // Store-type
            7'b1100011: imm_out = {{19{instruction[31]}}, instruction[7], instruction[30:25], instruction[11:8], 1'b0}; // B-type 
            7'b0110111: imm_out = {instruction[31:12], 12'b0}; // U-type
	        7'b0010111: imm_out = {instruction[31:12], 12'b0}; // U-type
            7'b1101111: imm_out = {{11{instruction[31]}}, instruction[19:12], instruction[20], instruction[30:21], 1'b0}; // J-type
 
            default: imm_out = 32'b0; // Default case
        endcase
    end

endmodule

project_1.srcs/sources_1/new/ALU.v
//////////////////////////////////////////////////////////////////////////////////
// Company: 
// Engineer: 
// 
// Create Date: 02/06/2025 10:47:49 AM
// Design Name: 
// Module Name: ALU
// Project Name: 
// Target Devices: 
// Tool Versions: 
// Description: 
// 
// Dependencies: 
// 
// Revision:
// Revision 0.01 - File Created
// Additional Comments:
// 
//////////////////////////////////////////////////////////////////////////////////

//  ALU
module ALU(
    input [31:0] A,             
    input [31:0] B,            
    input [3:0] ALUcontrol_In,          
    output reg [31:0] Result,   
    output reg Zero             
);

    always @(A or B or ALUcontrol_In) begin
        case (ALUcontrol_In)
            4'b0000: Result = A + B;           		// ADD
            4'b0001: Result = A - B;           		// SUB
            4'b0010: Result = A & B;           		// AND
            4'b0011: Result = A | B;           		// OR
            4'b0100: Result = A ^ B;           		// XOR
            4'b0101: Result = A << B[4:0];     		// SLL (Shift Left Logical)
            4'b0110: Result = A >> B[4:0];     		// SRL (Shift Right Logical)
            4'b0111: Result = $signed(A) >>> B[4:0];    // SRA (Shift Right Arithmetic)
            4'b1000: Result =($signed(A) < $signed(B)) ? 32'b1 : 32'b0;
            default: Result = 32'b0;          		
        endcase

        
        Zero = (Result == 32'b0) ? 1 : 0;
    end

endmodule

    // ALU Control
 module ALU_Control(        
        input [2:0] funct3,         
        input [6:0]funct7,        
        input [1:0] ALUOp,          
        output reg [3:0] ALUcontrol_Out 
    );
    always @(*) begin
      case ({ALUOp, funct7, funct3})
        12'b10_0000000_000 : ALUcontrol_Out <= 4'b0000;    // ADD 
        12'b00_0000000_000 : ALUcontrol_Out <= 4'b0000;    // ADD 
        12'b00_0000000_001 : ALUcontrol_Out <= 4'b0000;    // ADD 
        12'b00_0000000_010 : ALUcontrol_Out <= 4'b0000;    // ADD 
        12'b10_0100000_000 : ALUcontrol_Out <= 4'b0001;    // SUB 
        12'b10_0000000_111 : ALUcontrol_Out <= 4'b0010;    // AND
        12'b10_0000000_110 : ALUcontrol_Out <= 4'b0011;    // OR
        12'b10_0000000_100 : ALUcontrol_Out <= 4'b0100;    // XOR
        12'b10_0000000_001 : ALUcontrol_Out <= 4'b0101;    // SLL
        12'b10_0000000_101 : ALUcontrol_Out <= 4'b0110;    // SRL
        12'b10_0100000_101 : ALUcontrol_Out <= 4'b0111;    // SRA
        12'b10_0000000_010 : ALUcontrol_Out <= 4'b1000;    // SLT
        default            : ALUcontrol_Out <= 4'b0000; 
      endcase
    end
    
    
    endmodule

project_1.srcs/sources_1/new/control.v
//////////////////////////////////////////////////////////////////////////////////
// Company: 
// Engineer: 
// 
// Create Date: 02/06/2025 10:42:08 AM
// Design Name: 
// Module Name: control
// Project Name: 
// Target Devices: 
// Tool Versions: 
// Description: 
// 
// Dependencies: 
// 
// Revision:
// Revision 0.01 - File Created
// Additional Comments:
// 
//////////////////////////////////////////////////////////////////////////////////


// Control Unit

module main_control_unit(
    input [6:0] opcode,          
    output reg RegWrite,         
    output reg MemRead,          
    output reg MemWrite,         
    output reg MemToReg,        
    output reg ALUSrc,                      
    output reg Branch,                        
    output reg [1:0] ALUOp       
);

    always @(*) begin
        case (opcode)
            7'b0110011:  // R-type 
            begin  {ALUSrc, MemToReg, RegWrite, MemRead, MemWrite, Branch, ALUOp} <= {1'b0, 1'b0, 1'b1, 1'b0, 1'b0, 1'b0, 2'b10};end
            7'b0010011:   // I-type
            begin {ALUSrc, MemToReg, RegWrite, MemRead, MemWrite, Branch, ALUOp} <= {1'b1, 1'b0, 1'b1, 1'b0, 1'b0, 1'b0, 2'b10};end
            7'b0000011:   // Load 
            begin {ALUSrc, MemToReg, RegWrite, MemRead, MemWrite, Branch, ALUOp} <= {1'b1, 1'b1, 1'b1, 1'b1, 1'b0, 1'b0, 2'b00};end
            7'b0100011:   // Store 
            begin {ALUSrc, MemToReg, RegWrite, MemRead, MemWrite, Branch, ALUOp} <= {1'b1, 1'b0, 1'b0, 1'b0, 1'b1, 1'b0, 2'b00};end
            7'b1100011:   // Branch 
            begin {ALUSrc, MemToReg, RegWrite, MemRead, MemWrite, Branch, ALUOp} <= {1'b0, 1'b0, 1'b0, 1'b0, 1'b0, 1'b1, 2'b11};end  
            7'b1101111:   // Jump 
            begin  {ALUSrc, MemToReg, RegWrite, MemRead, MemWrite, Branch, ALUOp} <= {1'b0, 1'b0, 1'b1, 1'b0, 1'b0, 1'b0, 2'b10};end
            7'b0110111:   // LUI
            begin {ALUSrc, MemToReg, RegWrite, MemRead, MemWrite, Branch, ALUOp} <= {1'b0, 1'b0, 1'b1, 1'b0, 1'b0, 1'b0, 2'b10};end
            default: 
            begin {ALUSrc, MemToReg, RegWrite, MemRead, MemWrite, Branch, ALUOp} <= {1'b0, 1'b0, 1'b0, 1'b0, 1'b0, 1'b0, 2'b00};end  
        endcase
    end

endmodule

project_1.srcs/sources_1/new/Register.v
//////////////////////////////////////////////////////////////////////////////////
// Company: 
// Engineer: 
// 
// Create Date: 02/06/2025 09:25:23 AM
// Design Name: 
// Module Name: Register
// Project Name: 
// Target Devices: 
// Tool Versions: 
// Description: 
// 
// Dependencies: 
// 
// Revision:
// Revision 0.01 - File Created
// Additional Comments:
// 
//////////////////////////////////////////////////////////////////////////////////


module Register_File(clk, rst, RegWrite,Rs1,Rs2, Rd,Write_data,read_data1, read_data2);

input clk, rst, RegWrite;
input [4:0] Rs1,Rs2, Rd;
input [31:0] Write_data;
output [31:0] read_data1, read_data2;

reg [31:0] Registers [31:0];

 initial begin
Registers[0] = 0;
 Registers[1] = 3;
 Registers[2] = 2;
 Registers[3] = 12;
 Registers[4] = 20;
 Registers[5] = 3;
 Registers[6] = 44;
 Registers[7] = 4;
 Registers[8] = 2;
 Registers[9] = 1;
 Registers[10] = 23;
 Registers[11] = 4;
 Registers[12] = 90;
 Registers[13] = 10;
 Registers[14] = 20;
 Registers[15] = 30;
 Registers[16] = 40;
 Registers[17] = 50;
 Registers[18] = 60;
 Registers[19] = 70;
 Registers[20] = 80;
 Registers[21] = 80;
 Registers[22] = 90;
 Registers[23] = 70;
 Registers[24] = 60;
 Registers[25] = 65;
 Registers[26] = 4;
 Registers[27] = 32;
 Registers[28] = 12;
 Registers[29] = 34;
 Registers[30] = 5;
 Registers[31] = 10;
end

integer k;
always @(posedge clk) begin
if (rst) 
begin
      for (k = 0; k < 32; k = k + 1) begin
        Registers[k] = 32'b00;
      end
    end

    else if (RegWrite ) begin
      Registers[Rd] = Write_data;
    end
  end

  assign read_data1 = Registers[Rs1];
  assign read_data2 = Registers[Rs2];
endmodule

project_1.srcs/sources_1/new/PC.v
//////////////////////////////////////////////////////////////////////////////////
// Company: 
// Engineer: 
// 
// Create Date: 02/06/2025 09:06:22 AM
// Design Name: 
// Module Name: PC
// Project Name: 
// Target Devices: 
// Tool Versions: 
// Description: 
// 
// Dependencies: 
// 
// Revision:
// Revision 0.01 - File Created
// Additional Comments:
// 
//////////////////////////////////////////////////////////////////////////////////

module program_counter(
    input clk,                
    input rst,                
    input [31:0] pc_in,       
    output reg [31:0] pc_out 
);

    always @(posedge clk or posedge rst) begin
        if (rst) begin
            pc_out <= 32'b00;  
        end else begin
            pc_out <= pc_in;  
        end
    end

endmodule
//............................................PC Adder .......................................//
module pc_adder(
    input [31:0] pc_in,       
    output reg [31:0] pc_next 
);

    always @(*) begin
        pc_next = pc_in + 4;  
    end

endmodule

project_1.srcs/sources_1/new/main.v
`timescale 1ns / 10ps
//////////////////////////////////////////////////////////////////////////////////
// Company: 
// Engineer: 
// 
// Create Date: 02/06/2025 03:41:30 PM
// Design Name: 
// Module Name: main
// Project Name: 
// Target Devices: 
// Tool Versions: 
// Description: 
// 
// Dependencies: 
// 
// Revision:
// Revision 0.01 - File Created
// Additional Comments:
// 
//////////////////////////////////////////////////////////////////////////////////


module main(
		  input clk, rst
		); 
wire [31:0] PC_main, PC_next_main, PC_wire, Instruction_main, read_data1, read_data2_main, ALU_RESULT, branch_target, immgen_wire,muxtoAlu,read_data_wire,WB_data_wire;
wire RegWrite,ALUSrc, MemRead,MemWrite,MemToReg,Branch,Zero;
wire [1:0] ALUOp_wire;
wire [3:0] ALUcontrol_wire;

program_counter PC(.clk(clk),.rst(rst),.pc_in(PC_wire),.pc_out(PC_main));
pc_adder PC_Adder(.pc_in(PC_main),.pc_next(PC_next_main));
pc_mux pc_mux(.pc_in(PC_next_main),.pc_branch(branch_target),.pc_select(Branch&Zero),.pc_out(PC_wire));
Instruction_Memory Instr_Mem(.rst(rst),.clk(clk),.read_address(PC_main),.instruction_out(Instruction_main));
Register_File Reg_File(.rst(rst), .clk(clk), .RegWrite(RegWrite), .Rs1(Instruction_main[19:15]), .Rs2(Instruction_main[24:20]), .Rd(Instruction_main[11:7]), .Write_data(WB_data_wire), .read_data1(read_data1), .read_data2(read_data2_main));
main_control_unit Control_Unit(.opcode(Instruction_main[6:0]),.RegWrite(RegWrite),.MemRead(MemRead),.MemWrite(MemWrite),.MemToReg(MemToReg),.ALUSrc(ALUSrc),.Branch(Branch),.ALUOp(ALUOp_wire));
ALU_Control ALU_Control(.funct3(Instruction_main[14:12]),.funct7(Instruction_main[31:25]),.ALUOp(ALUOp_wire),.ALUcontrol_Out(ALUcontrol_wire));
ALU ALU(.A(read_data1),.B(muxtoAlu),.ALUcontrol_In(ALUcontrol_wire),.Result(ALU_RESULT),.Zero(Zero));
immediate_generator Imm_Gen(.instruction(Instruction_main),.imm_out(immgen_wire));
MUX2to1 Imm_Mux(.input0(read_data2_main),.input1(immgen_wire),.select(ALUSrc),.out(muxtoAlu));
Data_Memory Data_Mem(.clk(clk),.rst(rst),.MemRead(MemRead),.MemWrite(MemWrite),.address(ALU_RESULT),.write_data(read_data2_main),.read_data(read_data_wire));
MUX2to1_DataMemory WB_Mux(.input0(ALU_RESULT),.input1(read_data_wire),.select(MemToReg),.out(WB_data_wire));
Branch_Adder Branch_Adder(.PC(PC_main), .offset(immgen_wire), .branch_target(branch_target));






endmodule

project_1.srcs/sim_1/new/testbench.v
`timescale 1ns / 1ps
//////////////////////////////////////////////////////////////////////////////////
// Company: 
// Engineer: 
// 
// Create Date: 02/06/2025 05:02:13 PM
// Design Name: 
// Module Name: testbench
// Project Name: 
// Target Devices: 
// Tool Versions: 
// Description: 
// 
// Dependencies: 
// 
// Revision:
// Revision 0.01 - File Created
// Additional Comments:
// 
//////////////////////////////////////////////////////////////////////////////////


// Testbench for top module

module main_tb;

    reg clk, rst;
    
    main UUT (
        .clk(clk), 
        .rst(rst)
    );

    // Clock generation
    initial begin
        clk = 0;
    end

    always #50 clk = ~clk; 

    // Reset generation
    initial begin
        rst = 1'b1;
        #50;
        rst = 1'b0; 
        #5200; 
    end

    
    initial begin
        $dumpfile("waveform.vcd");  
        $dumpvars(0, UUT);          
    end

endmodule

project_1.sim/sim_1/behav/xsim/waveform.vcd
$date
   Wed Mar  5 20:18:52 2025
$end
$version
  2018.2
$end
$timescale
  1ps
$end
$scope module main_tb $end
$scope module UUT $end
$var wire 1 ! clk $end
$var wire 1 " rst $end
$var wire 32 # PC_main [31:0] $end
$var wire 32 $ PC_next_main [31:0] $end
$var wire 32 % PC_wire [31:0] $end
$var wire 32 & Instruction_main [31:0] $end
$var wire 32 ' read_data1 [31:0] $end
$var wire 32 ( read_data2_main [31:0] $end
$var wire 32 ) ALU_RESULT [31:0] $end
$var wire 32 * branch_target [31:0] $end
$var wire 32 + immgen_wire [31:0] $end
$var wire 32 , muxtoAlu [31:0] $end
$var wire 32 - read_data_wire [31:0] $end
$var wire 32 . WB_data_wire [31:0] $end
$var wire 1 / RegWrite $end
$var wire 1 0 ALUSrc $end
$var wire 1 1 MemRead $end
$var wire 1 2 MemWrite $end
$var wire 1 3 MemToReg $end
$var wire 1 4 Branch $end
$var wire 1 5 Zero $end
$var wire 2 6 ALUOp_wire [1:0] $end
$var wire 4 7 ALUcontrol_wire [3:0] $end
$scope module PC $end
$var wire 1 ! clk $end
$var wire 1 " rst $end
$var wire 32 % pc_in [31:0] $end
$var reg 32 8 pc_out [31:0] $end
$upscope $end
$scope module PC_Adder $end
$var wire 32 # pc_in [31:0] $end
$var reg 32 9 pc_next [31:0] $end
$upscope $end
$scope module pc_mux $end
$var wire 32 $ pc_in [31:0] $end
$var wire 32 * pc_branch [31:0] $end
$var wire 1 : pc_select $end
$var reg 32 ; pc_out [31:0] $end
$upscope $end
$scope module Instr_Mem $end
$var wire 1 " rst $end
$var wire 1 ! clk $end
$var wire 32 # read_address [31:0] $end
$var wire 32 & instruction_out [31:0] $end
$var integer 32 < k $end
$upscope $end
$scope module Reg_File $end
$var wire 1 ! clk $end
$var wire 1 " rst $end
$var wire 1 / RegWrite $end
$var wire 5 = Rs1 [4:0] $end
$var wire 5 > Rs2 [4:0] $end
$var wire 5 ? Rd [4:0] $end
$var wire 32 . Write_data [31:0] $end
$var wire 32 ' read_data1 [31:0] $end
$var wire 32 ( read_data2 [31:0] $end
$var integer 32 @ k $end
$upscope $end
$scope module Control_Unit $end
$var wire 7 A opcode [6:0] $end
$var reg 1 B RegWrite $end
$var reg 1 C MemRead $end
$var reg 1 D MemWrite $end
$var reg 1 E MemToReg $end
$var reg 1 F ALUSrc $end
$var reg 1 G Branch $end
$var reg 2 H ALUOp [1:0] $end
$upscope $end
$scope module ALU_Control $end
$var wire 3 I funct3 [2:0] $end
$var wire 7 J funct7 [6:0] $end
$var wire 2 6 ALUOp [1:0] $end
$var reg 4 K ALUcontrol_Out [3:0] $end
$upscope $end
$scope module ALU $end
$var wire 32 ' A [31:0] $end
$var wire 32 , B [31:0] $end
$var wire 4 7 ALUcontrol_In [3:0] $end
$var reg 32 L Result [31:0] $end
$var reg 1 M Zero $end
$upscope $end
$scope module Imm_Gen $end
$var wire 32 & instruction [31:0] $end
$var reg 32 N imm_out [31:0] $end
$upscope $end
$scope module Imm_Mux $end
$var wire 32 ( input0 [31:0] $end
$var wire 32 + input1 [31:0] $end
$var wire 1 0 select $end
$var wire 32 , out [31:0] $end
$upscope $end
$scope module Data_Mem $end
$var wire 1 ! clk $end
$var wire 1 " rst $end
$var wire 1 1 MemRead $end
$var wire 1 2 MemWrite $end
$var wire 32 ) address [31:0] $end
$var wire 32 ( write_data [31:0] $end
$var wire 32 - read_data [31:0] $end
$var integer 32 O k $end
$upscope $end
$scope module WB_Mux $end
$var wire 32 ) input0 [31:0] $end
$var wire 32 - input1 [31:0] $end
$var wire 1 3 select $end
$var wire 32 . out [31:0] $end
$upscope $end
$scope module Branch_Adder $end
$var wire 32 # PC [31:0] $end
$var wire 32 + offset [31:0] $end
$var reg 32 P branch_target [31:0] $end
$upscope $end
$upscope $end
$upscope $end
$enddefinitions $end
#0
$dumpvars
0!
1"
b0 #
b100 $
b100 %
b0 &
b0 '
b0 (
b0 )
b0 *
b0 +
b0 ,
b0 -
b0 .
0/
00
01
02
03
04
15
b0 6
b0 7
b0 8
b100 9
0:
b100 ;
b1000000 <
b0 =
b0 >
b0 ?
bx @
b0 A
0B
0C
0D
0E
0F
0G
b0 H
b0 I
b0 J
b0 K
b0 L
1M
b0 N
b1000000 O
b0 P
$end
#50000
1!
0"
b100 #
b1000 $
b1000 %
b1100110000000011010110011 &
b101000 '
b1000001 (
b1101001 )
b100 *
b1000001 ,
b0 -
b1101001 .
1/
05
b10 6
b100 8
b1000 9
0:
b1000 ;
b10000 =
b11001 >
b1101 ?
b110011 A
1B
b10 H
b0 I
b0 J
b1101001 L
0M
b0 N
b100 P
#100000
0!
#150000
1!
b1000 #
b1100 $
b1100 %
b1000000001101000000001010110011 &
b10 '
b1100 (
b11111111111111111111111111110110 )
b1000 *
b1100 ,
b0 -
b11111111111111111111111111110110 .
b1 7
b1000 8
b1100 9
b1100 ;
b1000 =
b11 >
b101 ?
b110011 A
b0 I
b100000 J
b1 K
b11111111111111111111111111110110 L
0M
b0 N
b1000 P
#200000
0!
#250000
1!
b1100 #
b10000 $
b10000 %
b1100010111000010110011 &
b10 '
b1100 (
b0 )
b1100 *
b0 -
b0 .
15
b10 7
b1100 8
b10000 9
0:
b10000 ;
b10 =
b11 >
b1 ?
b110011 A
b111 I
b0 J
b10 K
b0 L
1M
b0 N
b1100 P
#300000
0!
#350000
1!
b10000 #
b10100 $
b10100 %
b10100011110001000110011 &
b1100 '
b11111111111111111111111111110110 (
b11111111111111111111111111111110 )
b10000 *
b11111111111111111111111111110110 ,
b0 -
b11111111111111111111111111111110 .
05
b11 7
b10000 8
b10100 9
0:
b10100 ;
b11 =
b101 >
b100 ?
b110011 A
b110 I
b0 J
b11 K
b11111111111111111111111111111110 L
0M
b0 N
b10000 P
#400000
0!
#450000
1!
b10100 #
b11000 $
b11000 %
b10100011100001000110011 &
b1100 '
b11111111111111111111111111110110 (
b11111111111111111111111111111010 )
b10100 *
b0 -
b11111111111111111111111111111010 .
b100 7
b10100 8
b11000 9
b11000 ;
b11 =
b101 >
b100 ?
b110011 A
b100 I
b0 J
b100 K
b11111111111111111111111111111010 L
0M
b0 N
b10100 P
#500000
0!
#550000
1!
b11000 #
b11100 $
b11100 %
b10100011001001000110011 &
b1100 '
b11111111111111111111111111110110 (
b11000000000000000000000000 )
b11000 *
b0 -
b11000000000000000000000000 .
b101 7
b11000 8
b11100 9
b11100 ;
b11 =
b101 >
b100 ?
b110011 A
b1 I
b0 J
b101 K
b11000000000000000000000000 L
0M
b0 N
b11000 P
#600000
0!
#650000
1!
b11100 #
b100000 $
b100000 %
b10100011101001000110011 &
b1100 '
b11111111111111111111111111110110 (
b0 )
b11100 *
b0 -
b0 .
15
b110 7
b11100 8
b100000 9
0:
b100000 ;
b11 =
b101 >
b100 ?
b110011 A
b101 I
b0 J
b110 K
b0 L
1M
b0 N
b11100 P
#700000
0!
#750000
1!
b100000 #
b100100 $
b100100 %
b1000000001000011101001010110011 &
b1100 '
b10 (
b11 )
b100000 *
b10 ,
b0 -
b11 .
05
b111 7
b100000 8
b100100 9
0:
b100100 ;
b11 =
b10 >
b101 ?
b110011 A
b101 I
b100000 J
b111 K
b11 L
0M
b0 N
b100000 P
#800000
0!
#850000
1!
b100100 #
b101000 $
b101000 %
b1000011010001010110011 &
b1100 '
b10 (
b0 )
b100100 *
b0 -
b0 .
15
b1000 7
b100100 8
b101000 9
0:
b101000 ;
b11 =
b10 >
b101 ?
b110011 A
b10 I
b0 J
b1000 K
b0 L
1M
b0 N
b100100 P
#900000
0!
#950000
1!
b101000 #
b101100 $
b101100 %
b1010101000101100010011 &
b1010000 '
b10 (
b1010010 )
b101010 *
b10 +
b10 ,
b0 -
b1010010 .
10
05
b0 7
b101000 8
b101100 9
0:
b101100 ;
b10101 =
b10 >
b10110 ?
b10011 A
1F
b0 I
b0 J
b0 K
b1010010 L
0M
b10 N
b101010 P
#1000000
0!
#1050000
1!
b101100 #
b110000 $
b110000 %
b1101000110010010010011 &
b10 '
b1100 (
b11 )
b101111 *
b11 +
b11 ,
b0 -
b11 .
b11 7
b101100 8
b110000 9
b110000 ;
b1000 =
b11 >
b1001 ?
b10011 A
b110 I
b0 J
b11 K
b11 L
0M
b11 N
b101111 P
#1100000
0!
#1150000
1!
b110000 #
b110100 $
b110100 %
b10001000110010010010011 &
b10 '
b0 (
b110 )
b110100 *
b100 +
b100 ,
b0 -
b110 .
b110000 8
b110100 9
b110100 ;
b1000 =
b100 >
b1001 ?
b10011 A
b110 I
b0 J
b110 L
0M
b100 N
b110100 P
#1200000
0!
#1250000
1!
b110100 #
b111000 $
b111000 %
b10100010111000010010011 &
b10 '
b0 (
b0 )
b111001 *
b101 +
b101 ,
b0 -
b0 .
15
b10 7
b110100 8
b111000 9
0:
b111000 ;
b10 =
b101 >
b1 ?
b10011 A
b111 I
b0 J
b10 K
b0 L
1M
b101 N
b111001 P
#1300000
0!
#1350000
1!
b111000 #
b111100 $
b111100 %
b11000011001001000010011 &
b1100 '
b101100 (
b1100000000 )
b111110 *
b110 +
b110 ,
b0 -
b1100000000 .
05
b101 7
b111000 8
b111100 9
0:
b111100 ;
b11 =
b110 >
b100 ?
b10011 A
b1 I
b0 J
b101 K
b1100000000 L
0M
b110 N
b111110 P
#1400000
0!
#1450000
1!
b111100 #
b1000000 $
b1000000 %
b11100011101001000010011 &
b1100 '
b100 (
b0 )
b1000011 *
b111 +
b111 ,
b0 -
b0 .
15
b110 7
b111100 8
b1000000 9
0:
b1000000 ;
b11 =
b111 >
b100 ?
b10011 A
b101 I
b0 J
b110 K
b0 L
1M
b111 N
b1000011 P
#1500000
0!
#1550000
1!
b1000000 #
b1000100 $
b1000100 %
bx &
bx '
bx (
bx )
b1000000 *
b0 +
bx ,
b0 -
bx .
0/
00
x5
b0 6
b0 7
b1000000 8
b1000100 9
0:
b1000100 ;
bx =
bx >
bx ?
bx A
0B
0F
b0 H
bx I
bx J
b0 K
bx L
xM
b0 N
b1000000 P
#1600000
0!
#1650000
1!
b1000100 #
b1001000 $
b1001000 %
bx &
b1000100 *
b1000100 8
b1001000 9
b1001000 ;
bx =
bx >
bx ?
bx A
bx I
bx J
b1000100 P
